string_py/__init__.py
string_py/string_py.py
string_py-0.1.3.dist-info/METADATA
string_py-0.1.3.dist-info/WHEEL
string_py-0.1.3.dist-info/top_level.txt
string_py-0.1.3.dist-info/RECORD
