Metadata-Version: 2.1
Name: string-py
Version: 0.1.3
Summary: Utils for strings in python
Home-page: https://github.com/BabyEntchen/string_py
Author: BabyEntchen
Author-email: BabyEntchen <baby_entchen@web.de>
License: MIT
Project-URL: GitHub, https://github.com/BabyEntchen/string_py
Project-URL: Documentation, https://string-py.readthedocs.io
Keywords: python,string,strings,utils,string utils,random,random strings,formatting,formatter
Classifier: Programming Language :: Python :: 3
Requires-Python: >=3.10
